dsorm/__init__.py
dsorm/dsorm.py
dsorm-0.0.8.dist-info/LICENSE
dsorm-0.0.8.dist-info/METADATA
dsorm-0.0.8.dist-info/WHEEL
dsorm-0.0.8.dist-info/top_level.txt
dsorm-0.0.8.dist-info/RECORD
