Metadata-Version: 2.1
Name: dsorm
Version: 0.0.8
Summary: A Data Structure ORM
Home-page: https://github.com/kajuberdut/dsorm
Author: Patrick Shechet
Author-email: patrick.shechet@gmail.com
License: BSD
Platform: UNKNOWN
Classifier: Development Status :: 3 - Alpha
Classifier: License :: OSI Approved :: BSD License
Classifier: Programming Language :: Python :: 3.8
Classifier: Programming Language :: Python :: 3 :: Only
